geocoding/__init__.py
geocoding/core/__init__.py
geocoding/core/address_interpreter.py
geocoding/core/address_persister.py
geocoding/core/region_cache.py
geocoding/core/segmenter.py
geocoding/core/similarity_computer.py
geocoding/core/term_index_visitor.py
geocoding/core/segment/__init__.py
geocoding/core/segment/ascii_segmenter.py
geocoding/core/segment/jieba_analyzer_segmenter.py
geocoding/core/segment/simple_segmenter.py
geocoding/index/__init__.py
geocoding/index/term_index_builder.py
geocoding/index/term_index_entry.py
geocoding/index/term_index_item.py
geocoding/index/term_type.py
geocoding/model/__init__.py
geocoding/model/address.py
geocoding/model/address_entity.py
geocoding/model/division.py
geocoding/model/region_entity.py
geocoding/model/region_type.py
geocoding/resources/core/dict.dat
geocoding/resources/core/new_dict.dat
geocoding/resources/dic/community.txt
geocoding/resources/dic/region.txt
geocoding/resources/dic/stop.txt
geocoding/similarity/__init__.py
geocoding/similarity/document.py
geocoding/similarity/matched_result.py
geocoding/similarity/matched_term.py
geocoding/similarity/term.py
geocoding/utils/__init__.py
geocoding/utils/string_helper.py
pygeocoding-1.1.2.dist-info/LICENSE
pygeocoding-1.1.2.dist-info/METADATA
pygeocoding-1.1.2.dist-info/WHEEL
pygeocoding-1.1.2.dist-info/top_level.txt
pygeocoding-1.1.2.dist-info/RECORD
