Metadata-Version: 2.1
Name: pygeocoding
Version: 1.1.2
Summary: 地址标准化工具
Author: XiaoBai
Author-email: 1808269437@qq.com
License: MIT
Classifier: Programming Language :: Python :: 3
Requires-Python: >=3.6
License-File: LICENSE
Requires-Dist: jieba (>=0.42.1)
Requires-Dist: pandas (>=1.5.3)
